{
	"configurations" : 
	[
		{
			"directories" : 
			[
				{
					"build" : ".",
					"jsonFile" : "directory-.-Debug-d0094a50bb2071803777.json",
					"minimumCMakeVersion" : 
					{
						"string" : "3.16.0"
					},
					"projectIndex" : 0,
					"source" : ".",
					"targetIndexes" : 
					[
						0
					]
				}
			],
			"name" : "Debug",
			"projects" : 
			[
				{
					"directoryIndexes" : 
					[
						0
					],
					"name" : "xutils_unittests",
					"targetIndexes" : 
					[
						0
					]
				}
			],
			"targets" : 
			[
				{
					"directoryIndex" : 0,
					"id" : "xutils_unittests::@6890427a1f51a3e7e1df",
					"jsonFile" : "target-xutils_unittests-Debug-828c21321728a9944852.json",
					"name" : "xutils_unittests",
					"projectIndex" : 0
				}
			]
		}
	],
	"kind" : "codemodel",
	"paths" : 
	{
		"build" : "E:/Projects/GEN_FrameWork/Tests/XUtils_UnitTests/CMake/Build/Windows/intel32",
		"source" : "E:/Projects/GEN_FrameWork/Tests/XUtils_UnitTests/CMake"
	},
	"version" : 
	{
		"major" : 2,
		"minor" : 8
	}
}
